ensemble_hoax_news_detector/__init__.py
ensemble_hoax_news_detector/lime_explainer.py
ensemble_hoax_news_detector/model.py
ensemble_hoax_news_detector/assets/ensemble_model.joblib
ensemble_hoax_news_detector/assets/tfidf_vectorizer.joblib
ensemble_hoax_news_detector-0.2.dist-info/METADATA
ensemble_hoax_news_detector-0.2.dist-info/WHEEL
ensemble_hoax_news_detector-0.2.dist-info/top_level.txt
ensemble_hoax_news_detector-0.2.dist-info/RECORD
