Metadata-Version: 2.4
Name: ensemble-hoax-news-detector
Version: 0.2
Summary: Ensemble Learning Dalam Deteksi Berita Hoax Menggunakan XAI (LIME)
Home-page: https://github.com/uyaaaa/ensemble-hoax-news-detector
Author: Wayan Surya Adnyana
Author-email: wayansurya123@gmail.com
Classifier: Programming Language :: Python :: 3
Classifier: License :: OSI Approved :: MIT License
Classifier: Operating System :: OS Independent
Requires-Python: >=3.6
Requires-Dist: joblib
Requires-Dist: scikit-learn
Requires-Dist: lime
Requires-Dist: numpy
Requires-Dist: pandas
Dynamic: author
Dynamic: author-email
Dynamic: classifier
Dynamic: home-page
Dynamic: requires-dist
Dynamic: requires-python
Dynamic: summary
